astrosec/__init__.py
astrosec/auth.py
astrosec/generate.py
astrosec-0.0.1.dist-info/METADATA
astrosec-0.0.1.dist-info/WHEEL
astrosec-0.0.1.dist-info/top_level.txt
astrosec-0.0.1.dist-info/RECORD
